aula3_curso_fiap/__init__.py
aula3_curso_fiap/core.py
aula3_curso_fiap_package-1.0.0.dist-info/METADATA
aula3_curso_fiap_package-1.0.0.dist-info/WHEEL
aula3_curso_fiap_package-1.0.0.dist-info/top_level.txt
aula3_curso_fiap_package-1.0.0.dist-info/RECORD
