Metadata-Version: 2.4
Name: aula3_curso_fiap-package
Version: 1.0.0
Summary: Descricao da sua lib aula3_curso_fiap
Home-page: https://github.com/tadrianonet/aula3_curso_fiap
Author: seu nome
Author-email: seu.email@example.com
License: MIT
Dynamic: author
Dynamic: author-email
Dynamic: description
Dynamic: description-content-type
Dynamic: home-page
Dynamic: license
Dynamic: summary
